ramplot/__init__.py
ramplot/cli.py
ramplot/ramplot.py
ramplot/RamBoundry/MolprovityAllRegionGeneral.csv
ramplot/RamBoundry/MolprovityAllRegionGeneral3DBeta.csv
ramplot/RamBoundry/MolprovityAllRegionGly.csv
ramplot/RamBoundry/MolprovityAllRegionVal_Ile.csv
ramplot/RamBoundry/MolprovityAllRegioncisPro.csv
ramplot/RamBoundry/MolprovityAllRegionprePro.csv
ramplot/RamBoundry/MolprovityAllRegiontransPro.csv
ramplot-1.0.4.dist-info/LICENSE
ramplot-1.0.4.dist-info/METADATA
ramplot-1.0.4.dist-info/WHEEL
ramplot-1.0.4.dist-info/entry_points.txt
ramplot-1.0.4.dist-info/top_level.txt
ramplot-1.0.4.dist-info/RECORD
