Metadata-Version: 2.1
Name: ramplot
Version: 1.0.4
Summary: A brief description of your package.
Home-page: https://ramplot.in
Author: Mayank Kumar & R.S. Rathore
Author-email: mayank2801@gmail.com, rsrathore@cusb.ac.in
License: UNKNOWN
Keywords: Ramachandran plot,Protein structure analysis,Structural biology tools,Bioinformatics visualization,Protein conformation,Amino acid dihedrals,Torsion angle plots,Protein folding analysis,Structural bioinformatics,Protein modeling,Ramachandran plot software,Visualize protein structure,Protein backbone,angles,Phi and Psi angles,Protein structure validation,Molecular dynamics analysis,Protein secondary structure,Protein dihedral angles,Structural biology software,Protein structure research
Platform: UNKNOWN
Classifier: Development Status :: 5 - Production/Stable
Classifier: Intended Audience :: Science/Research
Classifier: Intended Audience :: Education
Classifier: Intended Audience :: Healthcare Industry
Classifier: License :: OSI Approved :: MIT License
Classifier: Programming Language :: Python :: 3
Classifier: Programming Language :: Python :: 3.7
Classifier: Programming Language :: Python :: 3.8
Classifier: Programming Language :: Python :: 3.9
Classifier: Programming Language :: Python :: 3.10
Classifier: Operating System :: OS Independent
Classifier: Topic :: Scientific/Engineering
Classifier: Topic :: Scientific/Engineering :: Bio-Informatics
Classifier: Topic :: Scientific/Engineering :: Chemistry
Classifier: Topic :: Scientific/Engineering :: Visualization
Classifier: Topic :: Software Development :: Libraries :: Python Modules
Classifier: Natural Language :: English
Requires-Python: >=3.6
License-File: LICENSE
Requires-Dist: numpy
Requires-Dist: pandas
Requires-Dist: biopython
Requires-Dist: matplotlib
Requires-Dist: mdanalysis
Requires-Dist: pytest-shutil
Requires-Dist: setuptools
